msalign/__init__.py
msalign/_version.py
msalign/align.py
msalign/utilities.py
tests/__init__.py
tests/test_init.py
tests/test_msalign.py
tests/test_utilities.py
msalign-0.2.0.dist-info/LICENSE
msalign-0.2.0.dist-info/METADATA
msalign-0.2.0.dist-info/WHEEL
msalign-0.2.0.dist-info/top_level.txt
msalign-0.2.0.dist-info/RECORD
