Metadata-Version: 2.1
Name: msalign
Version: 0.2.0
Summary: msalign: Signal calibration and alignment by reference peaks
Home-page: https://github.com/lukasz-migas/msalign
Author: Lukasz Migas
Author-email: lukas.migas@yahoo.com
License: Apache license 2.0
Download-URL: https://github.com/lukasz-migas/msalign
Platform: UNKNOWN
Classifier: Development Status :: 3 - Alpha
Classifier: Intended Audience :: Education
Classifier: Intended Audience :: Science/Research
Classifier: License :: OSI Approved :: MIT License
Classifier: Programming Language :: Python
Classifier: Programming Language :: Python :: 3 :: Only
Classifier: Programming Language :: Python :: 3.7
Classifier: Programming Language :: Python :: 3.8
Classifier: Programming Language :: Python :: 3.9
Classifier: Programming Language :: Python :: 3.10
Classifier: Topic :: Scientific/Engineering
Classifier: Topic :: Scientific/Engineering :: Information Analysis
Classifier: Topic :: Scientific/Engineering :: Bio-Informatics
Classifier: Operating System :: Microsoft :: Windows
Classifier: Operating System :: POSIX
Classifier: Operating System :: Unix
Classifier: Operating System :: MacOS
Requires-Python: >=3.7
Requires-Dist: numpy
Requires-Dist: scipy
Provides-Extra: deploy
Requires-Dist: wheel (>=0.34.2) ; extra == 'deploy'
Provides-Extra: dev
Requires-Dist: pre-commit (>=2.9.0) ; extra == 'dev'
Requires-Dist: isort ; extra == 'dev'
Requires-Dist: black (>=20.8b1) ; extra == 'dev'
Requires-Dist: flake8 (>=3.8.4) ; extra == 'dev'
Requires-Dist: check-manifest (>=0.42) ; extra == 'dev'
Requires-Dist: pytest ; extra == 'dev'
Requires-Dist: pytest-cov (>=2.8.1) ; extra == 'dev'
Requires-Dist: coverage (>=5.0.3) ; extra == 'dev'
Provides-Extra: testing
Requires-Dist: pytest ; extra == 'testing'
Requires-Dist: pytest-cov (>=2.8.1) ; extra == 'testing'
Requires-Dist: coverage (>=5.0.3) ; extra == 'testing'
Provides-Extra: web
Requires-Dist: markdown-changelog ; extra == 'web'
Requires-Dist: mkdocs ; extra == 'web'
Requires-Dist: mkdocs-material ; extra == 'web'
